vidcomp/__init__.py
vidcomp/main.py
vidcomp-0.1.dist-info/LICENSE
vidcomp-0.1.dist-info/METADATA
vidcomp-0.1.dist-info/WHEEL
vidcomp-0.1.dist-info/entry_points.txt
vidcomp-0.1.dist-info/top_level.txt
vidcomp-0.1.dist-info/RECORD
