Metadata-Version: 2.1
Name: vidcomp
Version: 0.1
Summary: A video comparison tool
Home-page: https://twitter.com/Lanaev0li
Author: Avinion
Author-email: shizofrin@gmail.com
Classifier: Programming Language :: Python :: 3
Classifier: License :: OSI Approved :: MIT License
Classifier: Operating System :: OS Independent
Requires-Python: >=3.6
License-File: LICENSE
